<?xml version="1.0"?>
<ruleset name="template coding standard">
    <arg value="p"/>
    <arg name="colors"/>
    <rule ref="PSR1">
        <exclude name="PSR1.Files.SideEffects.FoundWithSymbols"/>
    </rule>
    <rule ref="PSR12">
        <exclude name="PSR12.Files.OpenTag.NotAlone"/>
        <exclude name="PSR12.Files.FileHeader.SpacingAfterBlock"/>
        <exclude name="PSR12.Files.FileHeader.SpacingInsideBlock"/>
    </rule>
    <rule ref="Generic.NamingConventions.UpperCaseConstantName"/>
    <rule ref="Generic.ControlStructures.InlineControlStructure"/>
    <rule ref="Generic.Functions.CallTimePassByReference"/>
    <rule ref="Generic.NamingConventions.UpperCaseConstantName"/>
    <rule ref="Generic.PHP.LowerCaseConstant"/>
    <rule ref="Squiz.Arrays.ArrayBracketSpacing"/>
    <rule ref="Squiz.ControlStructures.ControlSignature"/>
    <rule ref="Squiz.ControlStructures.ForEachLoopDeclaration"/>
    <rule ref="Squiz.ControlStructures.ForLoopDeclaration"/>
    <rule ref="Squiz.ControlStructures.LowercaseDeclaration"/>
    <rule ref="Squiz.PHP.LowercasePHPFunctions"/>
    <rule ref="Squiz.Scope.MemberVarScope"/>

    <rule ref="Generic.PHP.ForbiddenFunctions">
        <properties>
            <property name="forbiddenFunctions"
                      type="array"
                      value="dump=>null,dd=>null,var_dump=>null,echo=>$output->writeln,die=>null,exit=>null"/>
        </properties>
    </rule>
    <rule ref="Squiz.PHP.CommentedOutCode">
        <properties>
            <property name="maxPercentage" value="60"/>
        </properties>
    </rule>


    <rule ref="Generic.Files.LineLength">
        <properties>
            <property name="lineLimit" value="160"/>
            <property name="absoluteLineLimit" value="180"/>
        </properties>
    </rule>

    <file>src</file>

    <exclude-pattern>*/client/*</exclude-pattern>
    <exclude-pattern>*/swagger-ui/*</exclude-pattern>
    <exclude-pattern>*/vendor/*</exclude-pattern>
    <exclude-pattern>*/node_modules/*</exclude-pattern>
    <exclude-pattern>*/config/*</exclude-pattern>
    <exclude-pattern>*/database/*</exclude-pattern>


    <config name="installed_paths" value="vendor/slevomat/coding-standard"/>
    <rule ref="SlevomatCodingStandard.Arrays.ArrayAccess"/>
    <rule ref="SlevomatCodingStandard.Arrays.MultiLineArrayEndBracketPlacement"/>
    <rule ref="SlevomatCodingStandard.Arrays.SingleLineArrayWhitespace">
        <properties>
            <property name="spacesAroundBrackets" value="0"/>
        </properties>
    </rule>
    <rule ref="SlevomatCodingStandard.Arrays.TrailingArrayComma"/>

    <rule ref="SlevomatCodingStandard.Attributes.DisallowAttributesJoining"/>
    <rule ref="SlevomatCodingStandard.Attributes.DisallowMultipleAttributesPerLine"/>
    <rule ref="SlevomatCodingStandard.Attributes.RequireAttributeAfterDocComment"/>

    <rule ref="SlevomatCodingStandard.Classes.BackedEnumTypeSpacing">
        <properties>
            <property name="spacesCountBeforeColon" value="0"/>
            <property name="spacesCountBeforeType" value="1"/>
        </properties>
    </rule>
    <rule ref="SlevomatCodingStandard.Classes.ClassConstantVisibility"/>
    <rule ref="SlevomatCodingStandard.Classes.EmptyLinesAroundClassBraces">
        <properties>
            <property name="linesCountAfterOpeningBrace" value="0"/>
            <property name="linesCountBeforeClosingBrace" value="0"/>
        </properties>
    </rule>
    <rule ref="SlevomatCodingStandard.Classes.MethodSpacing">
        <properties>
            <property name="minLinesCount" value="1"/>
            <property name="maxLinesCount" value="1"/>
        </properties>
    </rule>
    <rule ref="SlevomatCodingStandard.Classes.PropertyDeclaration">
        <properties>
            <property name="enableMultipleSpacesBetweenModifiersCheck"/>
        </properties>
    </rule>

    <rule ref="SlevomatCodingStandard.ControlStructures.AssignmentInCondition">
        <properties>
            <property name="ignoreAssignmentsInsideFunctionCalls"/>
        </properties>
    </rule>
    <rule ref="SlevomatCodingStandard.ControlStructures.DisallowTrailingMultiLineTernaryOperator"/>
    <rule ref="SlevomatCodingStandard.ControlStructures.RequireNullCoalesceOperator"/>
    <rule ref="SlevomatCodingStandard.ControlStructures.RequireShortTernaryOperator"/>
    <rule ref="SlevomatCodingStandard.ControlStructures.RequireTernaryOperator"/>
    <rule ref="SlevomatCodingStandard.ControlStructures.UselessIfConditionWithReturn"/>
    <rule ref="SlevomatCodingStandard.ControlStructures.UselessTernaryOperator"/>

    <rule ref="SlevomatCodingStandard.Exceptions.DeadCatch"/>

    <rule ref="SlevomatCodingStandard.Functions.DisallowEmptyFunction"/>
    <rule ref="SlevomatCodingStandard.Functions.NamedArgumentSpacing"/>
    <rule ref="SlevomatCodingStandard.Functions.UselessParameterDefaultValue"/>
    <rule ref="SlevomatCodingStandard.Namespaces.RequireOneNamespaceInFile"/>
    <rule ref="SlevomatCodingStandard.Namespaces.UseFromSameNamespace"/>
    <rule ref="SlevomatCodingStandard.Namespaces.UseDoesNotStartWithBackslash"/>
    <rule ref="SlevomatCodingStandard.Namespaces.UseSpacing">
        <properties>
            <property name="linesCountBeforeFirstUse" value="1"/>
            <property name="linesCountBetweenUseTypes" value="1"/>
            <property name="linesCountAfterLastUse" value="1"/>
        </properties>
    </rule>
    <rule ref="SlevomatCodingStandard.Namespaces.UselessAlias"/>
    <rule ref="SlevomatCodingStandard.Namespaces.UnusedUses">
        <properties>
            <property name="searchAnnotations" value="1"/>
        </properties>
    </rule>

    <rule ref="SlevomatCodingStandard.Operators.DisallowEqualOperators"/>
    <rule ref="SlevomatCodingStandard.Operators.RequireCombinedAssignmentOperator"/>
    <rule ref="SlevomatCodingStandard.Operators.RequireOnlyStandaloneIncrementAndDecrementOperators"/>

    <rule ref="SlevomatCodingStandard.PHP.UselessParentheses"/>
    <rule ref="SlevomatCodingStandard.PHP.UselessSemicolon"/>

    <rule ref="SlevomatCodingStandard.TypeHints.DeclareStrictTypes">
        <properties>
            <property name="declareOnFirstLine" value="1"/>
            <property name="spacesCountAroundEqualsSign" value="0"/>
        </properties>
    </rule>
    <rule ref="SlevomatCodingStandard.TypeHints.NullableTypeForNullDefaultValue"/>
    <rule ref="SlevomatCodingStandard.TypeHints.ParameterTypeHintSpacing"/>
    <rule ref="SlevomatCodingStandard.TypeHints.ReturnTypeHintSpacing">
        <properties>
            <property name="spacesCountBeforeColon" value="0"/>
        </properties>
    </rule>

    <rule ref="SlevomatCodingStandard.Variables.DisallowSuperGlobalVariable"/>
    <rule ref="SlevomatCodingStandard.Variables.DuplicateAssignmentToVariable"/>
    <rule ref="SlevomatCodingStandard.Variables.UselessVariable"/>

    <rule ref="SlevomatCodingStandard.Whitespaces.DuplicateSpaces"/>

    <rule ref="SlevomatCodingStandard.Functions.StrictCall"/>
</ruleset>
